ripgreppythonfiles/README.MD
ripgreppythonfiles/__init__.py
ripgreppythonfiles/requirements.txt
ripgreppythonfiles/thirdparty.json
ripgreppythonfiles-0.10.dist-info/LICENSE.rst
ripgreppythonfiles-0.10.dist-info/METADATA
ripgreppythonfiles-0.10.dist-info/WHEEL
ripgreppythonfiles-0.10.dist-info/top_level.txt
ripgreppythonfiles-0.10.dist-info/RECORD
