Metadata-Version: 2.1
Name: ripgreppythonfiles
Version: 0.10
Summary: Search for code in your env using ripgrep
Home-page: https://github.com/hansalemaos/ripgreppythonfiles
Author: Johannes Fischer
Author-email: aulasparticularesdealemaosp@gmail.com
License: MIT
Keywords: SEARCH,ripgrep,env
Classifier: Development Status :: 4 - Beta
Classifier: Programming Language :: Python :: 3 :: Only
Classifier: Programming Language :: Python :: 3.10
Classifier: Topic :: Software Development :: Libraries :: Python Modules
Classifier: Topic :: Utilities
License-File: LICENSE.rst
Requires-Dist: touchtouch
